CHANGELOG.rst
LICENSE
MANIFEST.in
README.rst
VERSION
configfetch.py
setup.py
configfetch.egg-info/PKG-INFO
configfetch.egg-info/SOURCES.txt
configfetch.egg-info/dependency_links.txt
configfetch.egg-info/not-zip-safe
configfetch.egg-info/requires.txt
configfetch.egg-info/top_level.txt